linktools/__init__.py
linktools/__main__.py
linktools/_config.py
linktools/_environ.py
linktools/_tools.py
linktools/_url.py
linktools/decorator.py
linktools/metadata.py
linktools/reactor.py
linktools/rich.py
linktools/ssh.py
linktools/types.py
linktools/assets/android-tools.apk
linktools/assets/android-tools.json
linktools/assets/browsers.json
linktools/assets/frida.js
linktools/assets/frida.min.js
linktools/assets/tools.json
linktools/assets/objection/plugins/__init__.py
linktools/cli/__init__.py
linktools/cli/argparse.py
linktools/cli/command.py
linktools/cli/env.py
linktools/cli/mobile.py
linktools/cli/update.py
linktools/cli/commands/__init__.py
linktools/cli/commands/android/__init__.py
linktools/cli/commands/android/adb.py
linktools/cli/commands/android/agent.py
linktools/cli/commands/android/app.py
linktools/cli/commands/android/cert.py
linktools/cli/commands/android/debug.py
linktools/cli/commands/android/frida.py
linktools/cli/commands/android/info.py
linktools/cli/commands/android/intent.py
linktools/cli/commands/android/objection.py
linktools/cli/commands/android/pidcat.py
linktools/cli/commands/android/top.py
linktools/cli/commands/common/__init__.py
linktools/cli/commands/common/env.py
linktools/cli/commands/common/grep.py
linktools/cli/commands/common/tools.py
linktools/cli/commands/ios/__init__.py
linktools/cli/commands/ios/frida.py
linktools/cli/commands/ios/ios.py
linktools/cli/commands/ios/ipa.py
linktools/cli/commands/ios/objection.py
linktools/cli/commands/ios/scp.py
linktools/cli/commands/ios/ssh.py
linktools/frida/__init__.py
linktools/frida/app.py
linktools/frida/script.py
linktools/frida/server.py
linktools/ida/__init__.py
linktools/ida/ida.py
linktools/mobile/__init__.py
linktools/mobile/_base.py
linktools/mobile/android/__init__.py
linktools/mobile/android/adb.py
linktools/mobile/android/scrcpy.py
linktools/mobile/android/types.py
linktools/mobile/harmony/__init__.py
linktools/mobile/harmony/hdc.py
linktools/mobile/ios/__init__.py
linktools-0.8.17.post0.dist-info/LICENSE
linktools-0.8.17.post0.dist-info/METADATA
linktools-0.8.17.post0.dist-info/WHEEL
linktools-0.8.17.post0.dist-info/entry_points.txt
linktools-0.8.17.post0.dist-info/top_level.txt
linktools-0.8.17.post0.dist-info/RECORD
