Metadata-Version: 2.2
Name: linktools
Version: 0.8.17.post0
Summary: linktools toolkit
Author-email: Hu Ji <669898595@qq.com>
License: Apache-2.0
Project-URL: Homepage, https://github.com/linktools-toolkit/linktools
Project-URL: Repository, https://github.com/linktools-toolkit/linktools.git
Requires-Python: >=3.6
License-File: LICENSE
Requires-Dist: rich
Requires-Dist: filelock>=3.4.0
Requires-Dist: importlib-metadata; python_version < "3.8"
Requires-Dist: psutil
Provides-Extra: requests
Requires-Dist: requests[socks]; extra == "requests"
Provides-Extra: frida
Requires-Dist: frida>=15.0.0; extra == "frida"
Provides-Extra: objection
Requires-Dist: objection; extra == "objection"
Provides-Extra: lief
Requires-Dist: lief>0.10.1; extra == "lief"
Requires-Dist: python-magic; platform_system == "Linux" and extra == "lief"
Requires-Dist: python-magic; platform_system == "Darwin" and extra == "lief"
Requires-Dist: python-magic-bin; platform_system == "Windows" and extra == "lief"
Provides-Extra: ssh
Requires-Dist: paramiko; extra == "ssh"
Requires-Dist: scp; extra == "ssh"
Provides-Extra: ssl
Requires-Dist: pyOpenSSL; extra == "ssl"
Provides-Extra: container
Requires-Dist: linktools-cntr; extra == "container"
Provides-Extra: argcomplete
Requires-Dist: argcomplete>=2.0.0; extra == "argcomplete"
Provides-Extra: all
Requires-Dist: requests[socks]; extra == "all"
Requires-Dist: frida>=15.0.0; extra == "all"
Requires-Dist: objection; extra == "all"
Requires-Dist: lief>0.10.1; extra == "all"
Requires-Dist: python-magic; platform_system == "Linux" and extra == "all"
Requires-Dist: python-magic; platform_system == "Darwin" and extra == "all"
Requires-Dist: python-magic-bin; platform_system == "Windows" and extra == "all"
Requires-Dist: paramiko; extra == "all"
Requires-Dist: scp; extra == "all"
Requires-Dist: pyOpenSSL; extra == "all"
Requires-Dist: linktools-cntr; extra == "all"
Requires-Dist: argcomplete>=2.0.0; extra == "all"
Requires-Dist: requests[socks]; extra == "all"
Requires-Dist: frida>=15.0.0; extra == "all"
Requires-Dist: objection; extra == "all"
Requires-Dist: lief>0.10.1; extra == "all"
Requires-Dist: python-magic; platform_system == "Linux" and extra == "all"
Requires-Dist: python-magic; platform_system == "Darwin" and extra == "all"
Requires-Dist: python-magic-bin; platform_system == "Windows" and extra == "all"
Requires-Dist: paramiko; extra == "all"
Requires-Dist: scp; extra == "all"
Requires-Dist: pyOpenSSL; extra == "all"
Requires-Dist: linktools-cntr; extra == "all"
Requires-Dist: argcomplete>=2.0.0; extra == "all"
Dynamic: provides-extra
Dynamic: requires-dist
